data/__init__.py
data/dataset.py
fine_tuning/BitFit.py
fine_tuning/ULMFiT.py
fine_tuning/__init__.py
fine_tuning/chain_thaw.py
fine_tuning/stlr.py
fine_tuning/utils.py
fine_tuning/vanilla_fine_tuning.py
parameter_efficient/__init__.py
parameter_efficient/adapter.py
parameter_efficient/adapter_bapna.py
parameter_efficient/adapterdrop.py
parameter_efficient/lora.py
parameter_efficient/mam_adapter.py
parameter_efficient/masking.py
parameter_efficient/parallel_adapter.py
parameter_efficient/prefix_tuning.py
parameter_efficient/prompt_tuning.py
tl_lib/__init__.py
tl_lib/evaluate.py
tl_lib/select_model.py
tl_lib/tl_train.py
tl_lib/utils.py
plamtral-0.0.9.dist-info/LICENSE
plamtral-0.0.9.dist-info/METADATA
plamtral-0.0.9.dist-info/WHEEL
plamtral-0.0.9.dist-info/top_level.txt
plamtral-0.0.9.dist-info/RECORD
