Metadata-Version: 2.1
Name: plamtral
Version: 0.0.9
Summary: A transfer learning library for pre-trained transformers.
Home-page: https://github.com/Vibhu04/plamtral
Author: Vibhu
Author-email: vibhud04@gmail.com
Project-URL: Bug Tracker, https://github.com/Vibhu04/plamtral/issues
Classifier: Programming Language :: Python :: 3
Classifier: License :: OSI Approved :: MIT License
Classifier: Operating System :: OS Independent
Requires-Python: >=3.6
License-File: LICENSE
Requires-Dist: nltk
Requires-Dist: torch
Requires-Dist: torchmetrics
Requires-Dist: tqdm
Requires-Dist: transformers
